forbidden_comments/__init__.py
forbidden_comments/__main__.py
forbidden_comments-0.1.0.dist-info/entry_points.txt
forbidden_comments-0.1.0.dist-info/WHEEL
forbidden_comments-0.1.0.dist-info/METADATA
forbidden_comments-0.1.0.dist-info/RECORD
